README.md
setup.py
cngi/__init__.py
cngi/_utils/__init__.py
cngi/_utils/_beams.py
cngi/_utils/_check_parms.py
cngi/_utils/_constants.py
cngi/_utils/_io.py
cngi/_utils/_join_split.py
cngi/_utils/_mxds_ops.py
cngi/_utils/_specials.py
cngi/_utils/_table_conversion.py
cngi/_utils/_table_conversion2.py
cngi/conversion/__init__.py
cngi/conversion/convert_image.py
cngi/conversion/convert_ms.py
cngi/conversion/convert_ms2.py
cngi/conversion/convert_table.py
cngi/conversion/describe_ms.py
cngi/conversion/read_ms.py
cngi/conversion/read_table.py
cngi/dio/__init__.py
cngi/dio/append_xds.py
cngi/dio/describe_vis.py
cngi/dio/read_image.py
cngi/dio/read_vis.py
cngi/dio/write_image.py
cngi/dio/write_vis.py
cngi/direct/__init__.py
cngi/direct/framework.py
cngi/image/__init__.py
cngi/image/cont_sub.py
cngi/image/fit_gaussian.py
cngi/image/fit_gaussian_rl.py
cngi/image/gaussian_beam.py
cngi/image/implot.py
cngi/image/make_empty_sky_image.py
cngi/image/mask.py
cngi/image/moments.py
cngi/image/rebin.py
cngi/image/reframe.py
cngi/image/region.py
cngi/image/smooth.py
cngi/image/spec_fit.py
cngi/image/statistics.py
cngi/image/stokes_to_corr.py
cngi/vis/__init__.py
cngi/vis/apply_flags.py
cngi/vis/chan_average.py
cngi/vis/chan_smooth.py
cngi/vis/join_dataset.py
cngi/vis/join_vis.py
cngi/vis/reframe.py
cngi/vis/split_dataset.py
cngi/vis/time_average.py
cngi/vis/uv_cont_fit.py
cngi/vis/visplot.py
cngi_prototype.egg-info/PKG-INFO
cngi_prototype.egg-info/SOURCES.txt
cngi_prototype.egg-info/dependency_links.txt
cngi_prototype.egg-info/requires.txt
cngi_prototype.egg-info/top_level.txt
ngcasa/__init__.py
ngcasa/_ngcasa_utils/__init__.py
ngcasa/calibration/__init__.py
ngcasa/calibration/apply_calibration.py
ngcasa/calibration/self_cal.py
ngcasa/calibration/_calibration_utils/__init__.py
ngcasa/calibration/_calibration_utils/_check_calibration_parms.py
ngcasa/deconvolution/__init__.py
ngcasa/deconvolution/deconvolve_adaptive_scale_pixel.py
ngcasa/deconvolution/deconvolve_fast_resolve.py
ngcasa/deconvolution/deconvolve_multiterm_clean.py
ngcasa/deconvolution/deconvolve_point_clean.py
ngcasa/deconvolution/deconvolve_rotation_measure_clean.py
ngcasa/deconvolution/feather.py
