Metadata-Version: 2.1
Name: cngi-prototype
Version: 1.0.1
Summary: CASA Next Generation Infrastructure Prototype
Home-page: https://github.com/casangi/cngi_prototype
Author: National Radio Astronomy Observatory
Author-email: casa-feedback@nrao.edu
License: Apache-2.0
Platform: UNKNOWN
Provides-Extra: dev
